pyinr/__init__.py
pyinr-0.0.5.dist-info/METADATA
pyinr-0.0.5.dist-info/WHEEL
pyinr-0.0.5.dist-info/licenses/LICENSE
pyinr-0.0.5.dist-info/RECORD
