Metadata-Version: 2.4
Name: pyinr
Version: 0.0.5
Summary: A simple package to convert Indian Rupees to other currencies.
Project-URL: Homepage, https://github.com/ganeshdatta23/pyinr
Project-URL: Bug Tracker, https://github.com/ganeshdatta23/pyinr/issues
Author-email: Ganesh Datta Padamata <ganeshdattapadamata@gmail.com>
License-File: LICENSE
Classifier: License :: OSI Approved :: MIT License
Classifier: Operating System :: OS Independent
Classifier: Programming Language :: Python :: 3
Requires-Python: >=3.7
